[
  {
    "orderId": "SilphCoOrder#002",
    "date": "2026-03-22T04:00:00.000Z",
    "customer": "Mike (Death187Knight)",
    "huntType": "Coins",
    "raidType": "",
    "pokemon": "15500 Coins",
    "quantity": "1",
    "coins": "15500",
    "itemPrice": 45,
    "paymentMethod": "PayPal",
    "otherRequests": "",
    "status": "Paid",
    "assignedAdmin": "Dan"
  },
  {
    "orderId": "SilphCoOrder#003",
    "date": "2026-03-23T04:00:00.000Z",
    "customer": "TJ (DrugDoc2000)",
    "huntType": "Coins",
    "raidType": "",
    "pokemon": "15500 Coins",
    "quantity": "1",
    "coins": "15500",
    "itemPrice": 45,
    "paymentMethod": "Venmo",
    "otherRequests": "",
    "status": "Paid",
    "assignedAdmin": "Dan"
  },
  {
    "orderId": "SilphCoOrder#004",
    "date": "2026-05-12T10:46:00.000Z",
    "customer": "Mike (Death187Knight)",
    "huntType": "Coins",
    "raidType": "",
    "pokemon": "15500 Coins",
    "quantity": "1",
    "coins": "15500",
    "itemPrice": 45,
    "paymentMethod": "PayPal",
    "otherRequests": "",
    "status": "Paid",
    "assignedAdmin": "Dan"
  },
  {
    "orderId": "SilphCoOrder#005",
    "date": "2026-05-29T17:15:00.000Z",
    "customer": "Chris (infvet05)",
    "huntType": "Coins",
    "raidType": "",
    "pokemon": "15500 Coins",
    "quantity": "1",
    "coins": "15500",
    "itemPrice": 45,
    "paymentMethod": "CashApp",
    "otherRequests": "",
    "status": "Paid",
    "assignedAdmin": "Dan"
  },
  {
    "orderId": "SilphCoOrder#006",
    "date": "2026-05-29T17:18:00.000Z",
    "customer": "Aaron (Aaron13524)",
    "huntType": "Shundo",
    "raidType": "",
    "pokemon": "Larvitar",
    "quantity": "1",
    "coins": "",
    "itemPrice": 5,
    "paymentMethod": "Venmo",
    "otherRequests": "",
    "status": "Paid",
    "assignedAdmin": "Dan"
  },
  {
    "orderId": "SilphCoOrder#007",
    "date": "2026-05-29T17:22:00.000Z",
    "customer": "Skate (Skatecrete)",
    "huntType": "Coins",
    "raidType": "",
    "pokemon": "31000 Coins",
    "quantity": "1",
    "coins": "31000",
    "itemPrice": 85,
    "paymentMethod": "CashApp",
    "otherRequests": "",
    "status": "Paid",
    "assignedAdmin": "Dan"
  },
  {
    "orderId": "SilphCoOrder#008",
    "date": "2026-05-29T20:52:00.000Z",
    "customer": "Mike (Death187Knight)",
    "huntType": "Coins",
    "raidType": "",
    "pokemon": "15500 Coins",
    "quantity": "1",
    "coins": "15500",
    "itemPrice": 45,
    "paymentMethod": "PayPal",
    "otherRequests": "",
    "status": "Paid",
    "assignedAdmin": "Dan"
  },
  {
    "orderId": "SilphCoOrder#009",
    "date": "2026-06-01T13:17:00.000Z",
    "customer": "other (other)",
    "huntType": "Go Fest",
    "raidType": "",
    "pokemon": "Go Fest",
    "quantity": "4",
    "coins": "",
    "itemPrice": 140,
    "paymentMethod": "Other",
    "otherRequests": "",
    "status": "Paid",
    "assignedAdmin": "Dan"
  },
  {
    "orderId": "SilphCoOrder#009",
    "date": "2026-06-01T13:17:00.000Z",
    "customer": "other (other)",
    "huntType": "Coins",
    "raidType": "",
    "pokemon": "31000 Coins",
    "quantity": "1",
    "coins": "31000",
    "itemPrice": 85,
    "paymentMethod": "Other",
    "otherRequests": "",
    "status": "Paid",
    "assignedAdmin": "Dan"
  },
  {
    "orderId": "SilphCoOrder#011",
    "date": "2026-06-01T13:17:00.000Z",
    "customer": "other (other)",
    "huntType": "Coins",
    "raidType": "",
    "pokemon": "15500 Coins",
    "quantity": "1",
    "coins": "15500",
    "itemPrice": 45,
    "paymentMethod": "Other",
    "otherRequests": "",
    "status": "Paid",
    "assignedAdmin": "Dan"
  },
  {
    "orderId": "SilphCoOrder#012",
    "date": "2026-06-01T13:40:00.000Z",
    "customer": "other (other)",
    "huntType": "Coins",
    "raidType": "",
    "pokemon": "31000 Coins",
    "quantity": "1",
    "coins": "31000",
    "itemPrice": 85,
    "paymentMethod": "Other",
    "otherRequests": "",
    "status": "Paid",
    "assignedAdmin": "Dan"
  }
]